<annotation>
	<folder></folder>
	<filename>46_44936_jpg.rf.69c78a5ac20befb2224c1b5154298324.jpg</filename>
	<path>46_44936_jpg.rf.69c78a5ac20befb2224c1b5154298324.jpg</path>
	<source>
		<database>roboflow.ai</database>
	</source>
	<size>
		<width>416</width>
		<height>416</height>
		<depth>3</depth>
	</size>
	<segmented>0</segmented>
	<object>
		<name>oscilloscope</name>
		<pose>Unspecified</pose>
		<truncated>0</truncated>
		<difficult>0</difficult>
		<occluded>0</occluded>
		<bndbox>
			<xmin>138</xmin>
			<xmax>308</xmax>
			<ymin>236</ymin>
			<ymax>415</ymax>
		</bndbox>
	</object>
	<object>
		<name>socket</name>
		<pose>Unspecified</pose>
		<truncated>0</truncated>
		<difficult>0</difficult>
		<occluded>0</occluded>
		<bndbox>
			<xmin>23</xmin>
			<xmax>93</xmax>
			<ymin>201</ymin>
			<ymax>282</ymax>
		</bndbox>
	</object>
	<object>
		<name>socket</name>
		<pose>Unspecified</pose>
		<truncated>0</truncated>
		<difficult>0</difficult>
		<occluded>0</occluded>
		<bndbox>
			<xmin>108</xmin>
			<xmax>151</xmax>
			<ymin>236</ymin>
			<ymax>318</ymax>
		</bndbox>
	</object>
	<object>
		<name>power supply</name>
		<pose>Unspecified</pose>
		<truncated>0</truncated>
		<difficult>0</difficult>
		<occluded>0</occluded>
		<bndbox>
			<xmin>2</xmin>
			<xmax>17</xmax>
			<ymin>164</ymin>
			<ymax>356</ymax>
		</bndbox>
	</object>
	<object>
		<name>hand</name>
		<pose>Unspecified</pose>
		<truncated>0</truncated>
		<difficult>0</difficult>
		<occluded>0</occluded>
		<bndbox>
			<xmin>298</xmin>
			<xmax>378</xmax>
			<ymin>293</ymin>
			<ymax>415</ymax>
		</bndbox>
	</object>
</annotation>
