<annotation>
	<folder></folder>
	<filename>49_34933_jpg.rf.7c88892cd98ad7fb8ab9ea83aef3ffb2.jpg</filename>
	<path>49_34933_jpg.rf.7c88892cd98ad7fb8ab9ea83aef3ffb2.jpg</path>
	<source>
		<database>roboflow.ai</database>
	</source>
	<size>
		<width>416</width>
		<height>416</height>
		<depth>3</depth>
	</size>
	<segmented>0</segmented>
	<object>
		<name>high voltage board</name>
		<pose>Unspecified</pose>
		<truncated>0</truncated>
		<difficult>0</difficult>
		<occluded>0</occluded>
		<bndbox>
			<xmin>230</xmin>
			<xmax>388</xmax>
			<ymin>227</ymin>
			<ymax>300</ymax>
		</bndbox>
	</object>
	<object>
		<name>oscilloscope probe tip</name>
		<pose>Unspecified</pose>
		<truncated>0</truncated>
		<difficult>0</difficult>
		<occluded>0</occluded>
		<bndbox>
			<xmin>2</xmin>
			<xmax>29</xmax>
			<ymin>90</ymin>
			<ymax>140</ymax>
		</bndbox>
	</object>
	<object>
		<name>oscilloscope</name>
		<pose>Unspecified</pose>
		<truncated>0</truncated>
		<difficult>0</difficult>
		<occluded>0</occluded>
		<bndbox>
			<xmin>31</xmin>
			<xmax>239</xmax>
			<ymin>1</ymin>
			<ymax>94</ymax>
		</bndbox>
	</object>
	<object>
		<name>working area</name>
		<pose>Unspecified</pose>
		<truncated>0</truncated>
		<difficult>0</difficult>
		<occluded>0</occluded>
		<bndbox>
			<xmin>106</xmin>
			<xmax>416</xmax>
			<ymin>202</ymin>
			<ymax>416</ymax>
		</bndbox>
	</object>
	<object>
		<name>hand</name>
		<pose>Unspecified</pose>
		<truncated>0</truncated>
		<difficult>0</difficult>
		<occluded>0</occluded>
		<bndbox>
			<xmin>115</xmin>
			<xmax>234</xmax>
			<ymin>170</ymin>
			<ymax>332</ymax>
		</bndbox>
	</object>
	<object>
		<name>hand</name>
		<pose>Unspecified</pose>
		<truncated>0</truncated>
		<difficult>0</difficult>
		<occluded>0</occluded>
		<bndbox>
			<xmin>214</xmin>
			<xmax>367</xmax>
			<ymin>52</ymin>
			<ymax>269</ymax>
		</bndbox>
	</object>
</annotation>
