<annotation>
	<folder></folder>
	<filename>49_51324_jpg.rf.ad71e4e151a81dfadeaa08be8fe69e2e.jpg</filename>
	<path>49_51324_jpg.rf.ad71e4e151a81dfadeaa08be8fe69e2e.jpg</path>
	<source>
		<database>roboflow.ai</database>
	</source>
	<size>
		<width>416</width>
		<height>416</height>
		<depth>3</depth>
	</size>
	<segmented>0</segmented>
	<object>
		<name>electric screwdriver</name>
		<pose>Unspecified</pose>
		<truncated>0</truncated>
		<difficult>0</difficult>
		<occluded>0</occluded>
		<bndbox>
			<xmin>181</xmin>
			<xmax>416</xmax>
			<ymin>2</ymin>
			<ymax>262</ymax>
		</bndbox>
	</object>
	<object>
		<name>oscilloscope</name>
		<pose>Unspecified</pose>
		<truncated>0</truncated>
		<difficult>0</difficult>
		<occluded>0</occluded>
		<bndbox>
			<xmin>1</xmin>
			<xmax>196</xmax>
			<ymin>1</ymin>
			<ymax>123</ymax>
		</bndbox>
	</object>
	<object>
		<name>working area</name>
		<pose>Unspecified</pose>
		<truncated>0</truncated>
		<difficult>0</difficult>
		<occluded>0</occluded>
		<bndbox>
			<xmin>77</xmin>
			<xmax>417</xmax>
			<ymin>223</ymin>
			<ymax>416</ymax>
		</bndbox>
	</object>
	<object>
		<name>high voltage board</name>
		<pose>Unspecified</pose>
		<truncated>0</truncated>
		<difficult>0</difficult>
		<occluded>0</occluded>
		<bndbox>
			<xmin>181</xmin>
			<xmax>373</xmax>
			<ymin>207</ymin>
			<ymax>279</ymax>
		</bndbox>
	</object>
	<object>
		<name>hand</name>
		<pose>Unspecified</pose>
		<truncated>0</truncated>
		<difficult>0</difficult>
		<occluded>0</occluded>
		<bndbox>
			<xmin>47</xmin>
			<xmax>161</xmax>
			<ymin>154</ymin>
			<ymax>364</ymax>
		</bndbox>
	</object>
	<object>
		<name>hand</name>
		<pose>Unspecified</pose>
		<truncated>0</truncated>
		<difficult>0</difficult>
		<occluded>0</occluded>
		<bndbox>
			<xmin>179</xmin>
			<xmax>363</xmax>
			<ymin>4</ymin>
			<ymax>177</ymax>
		</bndbox>
	</object>
</annotation>
