<annotation>
	<folder></folder>
	<filename>53_17121_jpg.rf.3b1316b75611fa7b6f8d6a46581daaf4.jpg</filename>
	<path>53_17121_jpg.rf.3b1316b75611fa7b6f8d6a46581daaf4.jpg</path>
	<source>
		<database>roboflow.ai</database>
	</source>
	<size>
		<width>416</width>
		<height>416</height>
		<depth>3</depth>
	</size>
	<segmented>0</segmented>
	<object>
		<name>oscilloscope probe tip</name>
		<pose>Unspecified</pose>
		<truncated>0</truncated>
		<difficult>0</difficult>
		<occluded>0</occluded>
		<bndbox>
			<xmin>125</xmin>
			<xmax>172</xmax>
			<ymin>2</ymin>
			<ymax>21</ymax>
		</bndbox>
	</object>
	<object>
		<name>low voltage board</name>
		<pose>Unspecified</pose>
		<truncated>0</truncated>
		<difficult>0</difficult>
		<occluded>0</occluded>
		<bndbox>
			<xmin>189</xmin>
			<xmax>416</xmax>
			<ymin>198</ymin>
			<ymax>415</ymax>
		</bndbox>
	</object>
	<object>
		<name>working area</name>
		<pose>Unspecified</pose>
		<truncated>0</truncated>
		<difficult>0</difficult>
		<occluded>0</occluded>
		<bndbox>
			<xmin>140</xmin>
			<xmax>416</xmax>
			<ymin>168</ymin>
			<ymax>414</ymax>
		</bndbox>
	</object>
	<object>
		<name>pliers</name>
		<pose>Unspecified</pose>
		<truncated>0</truncated>
		<difficult>0</difficult>
		<occluded>0</occluded>
		<bndbox>
			<xmin>388</xmin>
			<xmax>416</xmax>
			<ymin>1</ymin>
			<ymax>119</ymax>
		</bndbox>
	</object>
	<object>
		<name>hand</name>
		<pose>Unspecified</pose>
		<truncated>0</truncated>
		<difficult>0</difficult>
		<occluded>0</occluded>
		<bndbox>
			<xmin>203</xmin>
			<xmax>311</xmax>
			<ymin>249</ymin>
			<ymax>416</ymax>
		</bndbox>
	</object>
	<object>
		<name>hand</name>
		<pose>Unspecified</pose>
		<truncated>0</truncated>
		<difficult>0</difficult>
		<occluded>0</occluded>
		<bndbox>
			<xmin>103</xmin>
			<xmax>172</xmax>
			<ymin>284</ymin>
			<ymax>416</ymax>
		</bndbox>
	</object>
</annotation>
