<annotation>
	<folder></folder>
	<filename>53_48457_jpg.rf.2a3665dc6d9409bd16ed5f76474ae6a6.jpg</filename>
	<path>53_48457_jpg.rf.2a3665dc6d9409bd16ed5f76474ae6a6.jpg</path>
	<source>
		<database>roboflow.ai</database>
	</source>
	<size>
		<width>416</width>
		<height>416</height>
		<depth>3</depth>
	</size>
	<segmented>0</segmented>
	<object>
		<name>working area</name>
		<pose>Unspecified</pose>
		<truncated>0</truncated>
		<difficult>0</difficult>
		<occluded>0</occluded>
		<bndbox>
			<xmin>70</xmin>
			<xmax>416</xmax>
			<ymin>2</ymin>
			<ymax>416</ymax>
		</bndbox>
	</object>
	<object>
		<name>oscilloscope probe tip</name>
		<pose>Unspecified</pose>
		<truncated>0</truncated>
		<difficult>0</difficult>
		<occluded>0</occluded>
		<bndbox>
			<xmin>2</xmin>
			<xmax>63</xmax>
			<ymin>139</ymin>
			<ymax>342</ymax>
		</bndbox>
	</object>
	<object>
		<name>pliers</name>
		<pose>Unspecified</pose>
		<truncated>0</truncated>
		<difficult>0</difficult>
		<occluded>0</occluded>
		<bndbox>
			<xmin>86</xmin>
			<xmax>106</xmax>
			<ymin>381</ymin>
			<ymax>403</ymax>
		</bndbox>
	</object>
	<object>
		<name>screwdriver-</name>
		<pose>Unspecified</pose>
		<truncated>0</truncated>
		<difficult>0</difficult>
		<occluded>0</occluded>
		<bndbox>
			<xmin>200</xmin>
			<xmax>264</xmax>
			<ymin>125</ymin>
			<ymax>272</ymax>
		</bndbox>
	</object>
	<object>
		<name>hand</name>
		<pose>Unspecified</pose>
		<truncated>0</truncated>
		<difficult>0</difficult>
		<occluded>0</occluded>
		<bndbox>
			<xmin>188</xmin>
			<xmax>348</xmax>
			<ymin>96</ymin>
			<ymax>371</ymax>
		</bndbox>
	</object>
	<object>
		<name>hand</name>
		<pose>Unspecified</pose>
		<truncated>0</truncated>
		<difficult>0</difficult>
		<occluded>0</occluded>
		<bndbox>
			<xmin>111</xmin>
			<xmax>213</xmax>
			<ymin>193</ymin>
			<ymax>404</ymax>
		</bndbox>
	</object>
</annotation>
