<annotation>
	<folder></folder>
	<filename>53_6897_jpg.rf.99533b3d0259342c6c6bdc54430bbacc.jpg</filename>
	<path>53_6897_jpg.rf.99533b3d0259342c6c6bdc54430bbacc.jpg</path>
	<source>
		<database>roboflow.ai</database>
	</source>
	<size>
		<width>416</width>
		<height>416</height>
		<depth>3</depth>
	</size>
	<segmented>0</segmented>
	<object>
		<name>screwdriver-</name>
		<pose>Unspecified</pose>
		<truncated>0</truncated>
		<difficult>0</difficult>
		<occluded>0</occluded>
		<bndbox>
			<xmin>202</xmin>
			<xmax>249</xmax>
			<ymin>188</ymin>
			<ymax>267</ymax>
		</bndbox>
	</object>
	<object>
		<name>low voltage board</name>
		<pose>Unspecified</pose>
		<truncated>0</truncated>
		<difficult>0</difficult>
		<occluded>0</occluded>
		<bndbox>
			<xmin>164</xmin>
			<xmax>318</xmax>
			<ymin>51</ymin>
			<ymax>267</ymax>
		</bndbox>
	</object>
	<object>
		<name>working area</name>
		<pose>Unspecified</pose>
		<truncated>0</truncated>
		<difficult>0</difficult>
		<occluded>0</occluded>
		<bndbox>
			<xmin>109</xmin>
			<xmax>416</xmax>
			<ymin>64</ymin>
			<ymax>416</ymax>
		</bndbox>
	</object>
	<object>
		<name>pliers</name>
		<pose>Unspecified</pose>
		<truncated>0</truncated>
		<difficult>0</difficult>
		<occluded>0</occluded>
		<bndbox>
			<xmin>308</xmin>
			<xmax>342</xmax>
			<ymin>1</ymin>
			<ymax>23</ymax>
		</bndbox>
	</object>
	<object>
		<name>hand</name>
		<pose>Unspecified</pose>
		<truncated>0</truncated>
		<difficult>0</difficult>
		<occluded>0</occluded>
		<bndbox>
			<xmin>122</xmin>
			<xmax>189</xmax>
			<ymin>239</ymin>
			<ymax>381</ymax>
		</bndbox>
	</object>
	<object>
		<name>hand</name>
		<pose>Unspecified</pose>
		<truncated>0</truncated>
		<difficult>0</difficult>
		<occluded>0</occluded>
		<bndbox>
			<xmin>227</xmin>
			<xmax>366</xmax>
			<ymin>108</ymin>
			<ymax>302</ymax>
		</bndbox>
	</object>
</annotation>
