<annotation>
	<folder></folder>
	<filename>53_7268_jpg.rf.c0b113a3645d3b723d779efe647472a4.jpg</filename>
	<path>53_7268_jpg.rf.c0b113a3645d3b723d779efe647472a4.jpg</path>
	<source>
		<database>roboflow.ai</database>
	</source>
	<size>
		<width>416</width>
		<height>416</height>
		<depth>3</depth>
	</size>
	<segmented>0</segmented>
	<object>
		<name>low voltage board</name>
		<pose>Unspecified</pose>
		<truncated>0</truncated>
		<difficult>0</difficult>
		<occluded>0</occluded>
		<bndbox>
			<xmin>144</xmin>
			<xmax>325</xmax>
			<ymin>105</ymin>
			<ymax>334</ymax>
		</bndbox>
	</object>
	<object>
		<name>working area</name>
		<pose>Unspecified</pose>
		<truncated>0</truncated>
		<difficult>0</difficult>
		<occluded>0</occluded>
		<bndbox>
			<xmin>80</xmin>
			<xmax>410</xmax>
			<ymin>126</ymin>
			<ymax>416</ymax>
		</bndbox>
	</object>
	<object>
		<name>screwdriver-</name>
		<pose>Unspecified</pose>
		<truncated>0</truncated>
		<difficult>0</difficult>
		<occluded>0</occluded>
		<bndbox>
			<xmin>313</xmin>
			<xmax>416</xmax>
			<ymin>362</ymin>
			<ymax>415</ymax>
		</bndbox>
	</object>
	<object>
		<name>pliers</name>
		<pose>Unspecified</pose>
		<truncated>0</truncated>
		<difficult>0</difficult>
		<occluded>0</occluded>
		<bndbox>
			<xmin>305</xmin>
			<xmax>346</xmax>
			<ymin>1</ymin>
			<ymax>74</ymax>
		</bndbox>
	</object>
	<object>
		<name>oscilloscope probe tip</name>
		<pose>Unspecified</pose>
		<truncated>0</truncated>
		<difficult>0</difficult>
		<occluded>0</occluded>
		<bndbox>
			<xmin>70</xmin>
			<xmax>122</xmax>
			<ymin>1</ymin>
			<ymax>16</ymax>
		</bndbox>
	</object>
	<object>
		<name>hand</name>
		<pose>Unspecified</pose>
		<truncated>0</truncated>
		<difficult>0</difficult>
		<occluded>0</occluded>
		<bndbox>
			<xmin>108</xmin>
			<xmax>181</xmax>
			<ymin>318</ymin>
			<ymax>415</ymax>
		</bndbox>
	</object>
</annotation>
