<annotation>
	<folder></folder>
	<filename>55_18502_jpg.rf.c15a53ecc5db5c9adc2c6f8188745e16.jpg</filename>
	<path>55_18502_jpg.rf.c15a53ecc5db5c9adc2c6f8188745e16.jpg</path>
	<source>
		<database>roboflow.ai</database>
	</source>
	<size>
		<width>416</width>
		<height>416</height>
		<depth>3</depth>
	</size>
	<segmented>0</segmented>
	<object>
		<name>oscilloscope</name>
		<pose>Unspecified</pose>
		<truncated>0</truncated>
		<difficult>0</difficult>
		<occluded>0</occluded>
		<bndbox>
			<xmin>152</xmin>
			<xmax>338</xmax>
			<ymin>116</ymin>
			<ymax>354</ymax>
		</bndbox>
	</object>
	<object>
		<name>socket</name>
		<pose>Unspecified</pose>
		<truncated>0</truncated>
		<difficult>0</difficult>
		<occluded>0</occluded>
		<bndbox>
			<xmin>2</xmin>
			<xmax>78</xmax>
			<ymin>35</ymin>
			<ymax>150</ymax>
		</bndbox>
	</object>
	<object>
		<name>socket</name>
		<pose>Unspecified</pose>
		<truncated>0</truncated>
		<difficult>0</difficult>
		<occluded>0</occluded>
		<bndbox>
			<xmin>94</xmin>
			<xmax>168</xmax>
			<ymin>105</ymin>
			<ymax>226</ymax>
		</bndbox>
	</object>
	<object>
		<name>hand</name>
		<pose>Unspecified</pose>
		<truncated>0</truncated>
		<difficult>0</difficult>
		<occluded>0</occluded>
		<bndbox>
			<xmin>258</xmin>
			<xmax>317</xmax>
			<ymin>300</ymin>
			<ymax>414</ymax>
		</bndbox>
	</object>
</annotation>
