<annotation>
	<folder></folder>
	<filename>55_6064_jpg.rf.58aef654e936cecef58b954820ae383e.jpg</filename>
	<path>55_6064_jpg.rf.58aef654e936cecef58b954820ae383e.jpg</path>
	<source>
		<database>roboflow.ai</database>
	</source>
	<size>
		<width>416</width>
		<height>416</height>
		<depth>3</depth>
	</size>
	<segmented>0</segmented>
	<object>
		<name>electric screwdriver</name>
		<pose>Unspecified</pose>
		<truncated>0</truncated>
		<difficult>0</difficult>
		<occluded>0</occluded>
		<bndbox>
			<xmin>228</xmin>
			<xmax>416</xmax>
			<ymin>149</ymin>
			<ymax>416</ymax>
		</bndbox>
	</object>
	<object>
		<name>high voltage board</name>
		<pose>Unspecified</pose>
		<truncated>0</truncated>
		<difficult>0</difficult>
		<occluded>0</occluded>
		<bndbox>
			<xmin>56</xmin>
			<xmax>238</xmax>
			<ymin>295</ymin>
			<ymax>404</ymax>
		</bndbox>
	</object>
	<object>
		<name>working area</name>
		<pose>Unspecified</pose>
		<truncated>0</truncated>
		<difficult>0</difficult>
		<occluded>0</occluded>
		<bndbox>
			<xmin>1</xmin>
			<xmax>319</xmax>
			<ymin>326</ymin>
			<ymax>417</ymax>
		</bndbox>
	</object>
	<object>
		<name>welder station</name>
		<pose>Unspecified</pose>
		<truncated>0</truncated>
		<difficult>0</difficult>
		<occluded>0</occluded>
		<bndbox>
			<xmin>296</xmin>
			<xmax>374</xmax>
			<ymin>117</ymin>
			<ymax>215</ymax>
		</bndbox>
	</object>
	<object>
		<name>socket</name>
		<pose>Unspecified</pose>
		<truncated>0</truncated>
		<difficult>0</difficult>
		<occluded>0</occluded>
		<bndbox>
			<xmin>371</xmin>
			<xmax>392</xmax>
			<ymin>172</ymin>
			<ymax>211</ymax>
		</bndbox>
	</object>
	<object>
		<name>socket</name>
		<pose>Unspecified</pose>
		<truncated>0</truncated>
		<difficult>0</difficult>
		<occluded>0</occluded>
		<bndbox>
			<xmin>406</xmin>
			<xmax>415</xmax>
			<ymin>181</ymin>
			<ymax>222</ymax>
		</bndbox>
	</object>
	<object>
		<name>oscilloscope</name>
		<pose>Unspecified</pose>
		<truncated>0</truncated>
		<difficult>0</difficult>
		<occluded>0</occluded>
		<bndbox>
			<xmin>3</xmin>
			<xmax>155</xmax>
			<ymin>29</ymin>
			<ymax>197</ymax>
		</bndbox>
	</object>
	<object>
		<name>socket</name>
		<pose>Unspecified</pose>
		<truncated>0</truncated>
		<difficult>0</difficult>
		<occluded>0</occluded>
		<bndbox>
			<xmin>2</xmin>
			<xmax>12</xmax>
			<ymin>85</ymin>
			<ymax>149</ymax>
		</bndbox>
	</object>
	<object>
		<name>hand</name>
		<pose>Unspecified</pose>
		<truncated>0</truncated>
		<difficult>0</difficult>
		<occluded>0</occluded>
		<bndbox>
			<xmin>283</xmin>
			<xmax>410</xmax>
			<ymin>192</ymin>
			<ymax>363</ymax>
		</bndbox>
	</object>
</annotation>
