<annotation>
	<folder></folder>
	<filename>65_32923_jpg.rf.da6e8cd7cf4335fc8afcc94fa902cd24.jpg</filename>
	<path>65_32923_jpg.rf.da6e8cd7cf4335fc8afcc94fa902cd24.jpg</path>
	<source>
		<database>roboflow.ai</database>
	</source>
	<size>
		<width>416</width>
		<height>416</height>
		<depth>3</depth>
	</size>
	<segmented>0</segmented>
	<object>
		<name>working area</name>
		<pose>Unspecified</pose>
		<truncated>0</truncated>
		<difficult>0</difficult>
		<occluded>0</occluded>
		<bndbox>
			<xmin>94</xmin>
			<xmax>416</xmax>
			<ymin>159</ymin>
			<ymax>416</ymax>
		</bndbox>
	</object>
	<object>
		<name>oscilloscope</name>
		<pose>Unspecified</pose>
		<truncated>0</truncated>
		<difficult>0</difficult>
		<occluded>0</occluded>
		<bndbox>
			<xmin>118</xmin>
			<xmax>252</xmax>
			<ymin>4</ymin>
			<ymax>49</ymax>
		</bndbox>
	</object>
	<object>
		<name>high voltage board</name>
		<pose>Unspecified</pose>
		<truncated>0</truncated>
		<difficult>0</difficult>
		<occluded>0</occluded>
		<bndbox>
			<xmin>201</xmin>
			<xmax>368</xmax>
			<ymin>158</ymin>
			<ymax>251</ymax>
		</bndbox>
	</object>
	<object>
		<name>electric screwdriver</name>
		<pose>Unspecified</pose>
		<truncated>0</truncated>
		<difficult>0</difficult>
		<occluded>0</occluded>
		<bndbox>
			<xmin>216</xmin>
			<xmax>416</xmax>
			<ymin>2</ymin>
			<ymax>251</ymax>
		</bndbox>
	</object>
	<object>
		<name>oscilloscope probe tip</name>
		<pose>Unspecified</pose>
		<truncated>0</truncated>
		<difficult>0</difficult>
		<occluded>0</occluded>
		<bndbox>
			<xmin>109</xmin>
			<xmax>179</xmax>
			<ymin>112</ymin>
			<ymax>133</ymax>
		</bndbox>
	</object>
	<object>
		<name>hand</name>
		<pose>Unspecified</pose>
		<truncated>0</truncated>
		<difficult>0</difficult>
		<occluded>0</occluded>
		<bndbox>
			<xmin>130</xmin>
			<xmax>218</xmax>
			<ymin>153</ymin>
			<ymax>275</ymax>
		</bndbox>
	</object>
	<object>
		<name>hand</name>
		<pose>Unspecified</pose>
		<truncated>0</truncated>
		<difficult>0</difficult>
		<occluded>0</occluded>
		<bndbox>
			<xmin>268</xmin>
			<xmax>409</xmax>
			<ymin>9</ymin>
			<ymax>156</ymax>
		</bndbox>
	</object>
</annotation>
