<annotation>
	<folder></folder>
	<filename>65_50203_jpg.rf.b69837006385440822802af8bf66c9cc.jpg</filename>
	<path>65_50203_jpg.rf.b69837006385440822802af8bf66c9cc.jpg</path>
	<source>
		<database>roboflow.ai</database>
	</source>
	<size>
		<width>416</width>
		<height>416</height>
		<depth>3</depth>
	</size>
	<segmented>0</segmented>
	<object>
		<name>electric screwdriver</name>
		<pose>Unspecified</pose>
		<truncated>0</truncated>
		<difficult>0</difficult>
		<occluded>0</occluded>
		<bndbox>
			<xmin>185</xmin>
			<xmax>392</xmax>
			<ymin>1</ymin>
			<ymax>282</ymax>
		</bndbox>
	</object>
	<object>
		<name>oscilloscope</name>
		<pose>Unspecified</pose>
		<truncated>0</truncated>
		<difficult>0</difficult>
		<occluded>0</occluded>
		<bndbox>
			<xmin>2</xmin>
			<xmax>122</xmax>
			<ymin>3</ymin>
			<ymax>107</ymax>
		</bndbox>
	</object>
	<object>
		<name>oscilloscope probe tip</name>
		<pose>Unspecified</pose>
		<truncated>0</truncated>
		<difficult>0</difficult>
		<occluded>0</occluded>
		<bndbox>
			<xmin>2</xmin>
			<xmax>75</xmax>
			<ymin>174</ymin>
			<ymax>224</ymax>
		</bndbox>
	</object>
	<object>
		<name>high voltage board</name>
		<pose>Unspecified</pose>
		<truncated>0</truncated>
		<difficult>0</difficult>
		<occluded>0</occluded>
		<bndbox>
			<xmin>101</xmin>
			<xmax>201</xmax>
			<ymin>181</ymin>
			<ymax>274</ymax>
		</bndbox>
	</object>
	<object>
		<name>welder station</name>
		<pose>Unspecified</pose>
		<truncated>0</truncated>
		<difficult>0</difficult>
		<occluded>0</occluded>
		<bndbox>
			<xmin>285</xmin>
			<xmax>369</xmax>
			<ymin>4</ymin>
			<ymax>55</ymax>
		</bndbox>
	</object>
	<object>
		<name>socket</name>
		<pose>Unspecified</pose>
		<truncated>0</truncated>
		<difficult>0</difficult>
		<occluded>0</occluded>
		<bndbox>
			<xmin>369</xmin>
			<xmax>378</xmax>
			<ymin>6</ymin>
			<ymax>46</ymax>
		</bndbox>
	</object>
	<object>
		<name>socket</name>
		<pose>Unspecified</pose>
		<truncated>0</truncated>
		<difficult>0</difficult>
		<occluded>0</occluded>
		<bndbox>
			<xmin>387</xmin>
			<xmax>416</xmax>
			<ymin>2</ymin>
			<ymax>49</ymax>
		</bndbox>
	</object>
	<object>
		<name>welder base</name>
		<pose>Unspecified</pose>
		<truncated>0</truncated>
		<difficult>0</difficult>
		<occluded>0</occluded>
		<bndbox>
			<xmin>393</xmin>
			<xmax>416</xmax>
			<ymin>32</ymin>
			<ymax>60</ymax>
		</bndbox>
	</object>
	<object>
		<name>working area</name>
		<pose>Unspecified</pose>
		<truncated>0</truncated>
		<difficult>0</difficult>
		<occluded>0</occluded>
		<bndbox>
			<xmin>2</xmin>
			<xmax>317</xmax>
			<ymin>226</ymin>
			<ymax>415</ymax>
		</bndbox>
	</object>
	<object>
		<name>hand</name>
		<pose>Unspecified</pose>
		<truncated>0</truncated>
		<difficult>0</difficult>
		<occluded>0</occluded>
		<bndbox>
			<xmin>97</xmin>
			<xmax>196</xmax>
			<ymin>154</ymin>
			<ymax>282</ymax>
		</bndbox>
	</object>
	<object>
		<name>hand</name>
		<pose>Unspecified</pose>
		<truncated>0</truncated>
		<difficult>0</difficult>
		<occluded>0</occluded>
		<bndbox>
			<xmin>243</xmin>
			<xmax>371</xmax>
			<ymin>46</ymin>
			<ymax>187</ymax>
		</bndbox>
	</object>
</annotation>
