<annotation>
	<folder></folder>
	<filename>65_53381_jpg.rf.993a94f9f3e43bec27698bc32a8ba6f5.jpg</filename>
	<path>65_53381_jpg.rf.993a94f9f3e43bec27698bc32a8ba6f5.jpg</path>
	<source>
		<database>roboflow.ai</database>
	</source>
	<size>
		<width>416</width>
		<height>416</height>
		<depth>3</depth>
	</size>
	<segmented>0</segmented>
	<object>
		<name>register</name>
		<pose>Unspecified</pose>
		<truncated>0</truncated>
		<difficult>0</difficult>
		<occluded>0</occluded>
		<bndbox>
			<xmin>44</xmin>
			<xmax>213</xmax>
			<ymin>127</ymin>
			<ymax>348</ymax>
		</bndbox>
	</object>
	<object>
		<name>screwdriver-</name>
		<pose>Unspecified</pose>
		<truncated>0</truncated>
		<difficult>0</difficult>
		<occluded>0</occluded>
		<bndbox>
			<xmin>229</xmin>
			<xmax>318</xmax>
			<ymin>240</ymin>
			<ymax>322</ymax>
		</bndbox>
	</object>
	<object>
		<name>pliers</name>
		<pose>Unspecified</pose>
		<truncated>0</truncated>
		<difficult>0</difficult>
		<occluded>0</occluded>
		<bndbox>
			<xmin>267</xmin>
			<xmax>345</xmax>
			<ymin>305</ymin>
			<ymax>384</ymax>
		</bndbox>
	</object>
	<object>
		<name>working area</name>
		<pose>Unspecified</pose>
		<truncated>0</truncated>
		<difficult>0</difficult>
		<occluded>0</occluded>
		<bndbox>
			<xmin>348</xmin>
			<xmax>417</xmax>
			<ymin>167</ymin>
			<ymax>415</ymax>
		</bndbox>
	</object>
	<object>
		<name>oscilloscope</name>
		<pose>Unspecified</pose>
		<truncated>0</truncated>
		<difficult>0</difficult>
		<occluded>0</occluded>
		<bndbox>
			<xmin>379</xmin>
			<xmax>416</xmax>
			<ymin>1</ymin>
			<ymax>106</ymax>
		</bndbox>
	</object>
	<object>
		<name>socket</name>
		<pose>Unspecified</pose>
		<truncated>0</truncated>
		<difficult>0</difficult>
		<occluded>0</occluded>
		<bndbox>
			<xmin>337</xmin>
			<xmax>378</xmax>
			<ymin>7</ymin>
			<ymax>63</ymax>
		</bndbox>
	</object>
	<object>
		<name>socket</name>
		<pose>Unspecified</pose>
		<truncated>0</truncated>
		<difficult>0</difficult>
		<occluded>0</occluded>
		<bndbox>
			<xmin>274</xmin>
			<xmax>318</xmax>
			<ymin>1</ymin>
			<ymax>45</ymax>
		</bndbox>
	</object>
	<object>
		<name>power supply</name>
		<pose>Unspecified</pose>
		<truncated>0</truncated>
		<difficult>0</difficult>
		<occluded>0</occluded>
		<bndbox>
			<xmin>213</xmin>
			<xmax>255</xmax>
			<ymin>2</ymin>
			<ymax>87</ymax>
		</bndbox>
	</object>
	<object>
		<name>hand</name>
		<pose>Unspecified</pose>
		<truncated>0</truncated>
		<difficult>0</difficult>
		<occluded>0</occluded>
		<bndbox>
			<xmin>157</xmin>
			<xmax>246</xmax>
			<ymin>250</ymin>
			<ymax>383</ymax>
		</bndbox>
	</object>
</annotation>
