<annotation>
	<folder></folder>
	<filename>66_18959_jpg.rf.9876d4feaec2f2f63c5fd8be02704a4a.jpg</filename>
	<path>66_18959_jpg.rf.9876d4feaec2f2f63c5fd8be02704a4a.jpg</path>
	<source>
		<database>roboflow.ai</database>
	</source>
	<size>
		<width>416</width>
		<height>416</height>
		<depth>3</depth>
	</size>
	<segmented>0</segmented>
	<object>
		<name>screwdriver-</name>
		<pose>Unspecified</pose>
		<truncated>0</truncated>
		<difficult>0</difficult>
		<occluded>0</occluded>
		<bndbox>
			<xmin>212</xmin>
			<xmax>226</xmax>
			<ymin>154</ymin>
			<ymax>233</ymax>
		</bndbox>
	</object>
	<object>
		<name>low voltage board</name>
		<pose>Unspecified</pose>
		<truncated>0</truncated>
		<difficult>0</difficult>
		<occluded>0</occluded>
		<bndbox>
			<xmin>210</xmin>
			<xmax>349</xmax>
			<ymin>147</ymin>
			<ymax>275</ymax>
		</bndbox>
	</object>
	<object>
		<name>working area</name>
		<pose>Unspecified</pose>
		<truncated>0</truncated>
		<difficult>0</difficult>
		<occluded>0</occluded>
		<bndbox>
			<xmin>84</xmin>
			<xmax>416</xmax>
			<ymin>124</ymin>
			<ymax>416</ymax>
		</bndbox>
	</object>
	<object>
		<name>oscilloscope probe tip</name>
		<pose>Unspecified</pose>
		<truncated>0</truncated>
		<difficult>0</difficult>
		<occluded>0</occluded>
		<bndbox>
			<xmin>126</xmin>
			<xmax>196</xmax>
			<ymin>86</ymin>
			<ymax>132</ymax>
		</bndbox>
	</object>
	<object>
		<name>oscilloscope</name>
		<pose>Unspecified</pose>
		<truncated>0</truncated>
		<difficult>0</difficult>
		<occluded>0</occluded>
		<bndbox>
			<xmin>122</xmin>
			<xmax>229</xmax>
			<ymin>2</ymin>
			<ymax>45</ymax>
		</bndbox>
	</object>
	<object>
		<name>welder station</name>
		<pose>Unspecified</pose>
		<truncated>0</truncated>
		<difficult>0</difficult>
		<occluded>0</occluded>
		<bndbox>
			<xmin>393</xmin>
			<xmax>416</xmax>
			<ymin>2</ymin>
			<ymax>22</ymax>
		</bndbox>
	</object>
	<object>
		<name>hand</name>
		<pose>Unspecified</pose>
		<truncated>0</truncated>
		<difficult>0</difficult>
		<occluded>0</occluded>
		<bndbox>
			<xmin>49</xmin>
			<xmax>170</xmax>
			<ymin>227</ymin>
			<ymax>373</ymax>
		</bndbox>
	</object>
	<object>
		<name>hand</name>
		<pose>Unspecified</pose>
		<truncated>0</truncated>
		<difficult>0</difficult>
		<occluded>0</occluded>
		<bndbox>
			<xmin>197</xmin>
			<xmax>302</xmax>
			<ymin>2</ymin>
			<ymax>194</ymax>
		</bndbox>
	</object>
</annotation>
