<annotation>
	<folder></folder>
	<filename>86_20176_jpg.rf.23423296128dd4b4dd9db497e7e3fe40.jpg</filename>
	<path>86_20176_jpg.rf.23423296128dd4b4dd9db497e7e3fe40.jpg</path>
	<source>
		<database>roboflow.ai</database>
	</source>
	<size>
		<width>416</width>
		<height>416</height>
		<depth>3</depth>
	</size>
	<segmented>0</segmented>
	<object>
		<name>low voltage board</name>
		<pose>Unspecified</pose>
		<truncated>0</truncated>
		<difficult>0</difficult>
		<occluded>0</occluded>
		<bndbox>
			<xmin>125</xmin>
			<xmax>321</xmax>
			<ymin>318</ymin>
			<ymax>416</ymax>
		</bndbox>
	</object>
	<object>
		<name>socket</name>
		<pose>Unspecified</pose>
		<truncated>0</truncated>
		<difficult>0</difficult>
		<occluded>0</occluded>
		<bndbox>
			<xmin>1</xmin>
			<xmax>18</xmax>
			<ymin>77</ymin>
			<ymax>146</ymax>
		</bndbox>
	</object>
	<object>
		<name>oscilloscope</name>
		<pose>Unspecified</pose>
		<truncated>0</truncated>
		<difficult>0</difficult>
		<occluded>0</occluded>
		<bndbox>
			<xmin>32</xmin>
			<xmax>225</xmax>
			<ymin>65</ymin>
			<ymax>241</ymax>
		</bndbox>
	</object>
	<object>
		<name>welder station</name>
		<pose>Unspecified</pose>
		<truncated>0</truncated>
		<difficult>0</difficult>
		<occluded>0</occluded>
		<bndbox>
			<xmin>398</xmin>
			<xmax>416</xmax>
			<ymin>72</ymin>
			<ymax>206</ymax>
		</bndbox>
	</object>
	<object>
		<name>oscilloscope probe tip</name>
		<pose>Unspecified</pose>
		<truncated>0</truncated>
		<difficult>0</difficult>
		<occluded>0</occluded>
		<bndbox>
			<xmin>165</xmin>
			<xmax>200</xmax>
			<ymin>380</ymin>
			<ymax>415</ymax>
		</bndbox>
	</object>
	<object>
		<name>working area</name>
		<pose>Unspecified</pose>
		<truncated>0</truncated>
		<difficult>0</difficult>
		<occluded>0</occluded>
		<bndbox>
			<xmin>81</xmin>
			<xmax>416</xmax>
			<ymin>328</ymin>
			<ymax>416</ymax>
		</bndbox>
	</object>
	<object>
		<name>hand</name>
		<pose>Unspecified</pose>
		<truncated>0</truncated>
		<difficult>0</difficult>
		<occluded>0</occluded>
		<bndbox>
			<xmin>201</xmin>
			<xmax>314</xmax>
			<ymin>192</ymin>
			<ymax>373</ymax>
		</bndbox>
	</object>
	<object>
		<name>hand</name>
		<pose>Unspecified</pose>
		<truncated>0</truncated>
		<difficult>0</difficult>
		<occluded>0</occluded>
		<bndbox>
			<xmin>121</xmin>
			<xmax>167</xmax>
			<ymin>402</ymin>
			<ymax>416</ymax>
		</bndbox>
	</object>
</annotation>
