<annotation>
	<folder></folder>
	<filename>86_5316_jpg.rf.cc12082e4986d7c878ee3d43312c50a0.jpg</filename>
	<path>86_5316_jpg.rf.cc12082e4986d7c878ee3d43312c50a0.jpg</path>
	<source>
		<database>roboflow.ai</database>
	</source>
	<size>
		<width>416</width>
		<height>416</height>
		<depth>3</depth>
	</size>
	<segmented>0</segmented>
	<object>
		<name>socket</name>
		<pose>Unspecified</pose>
		<truncated>0</truncated>
		<difficult>0</difficult>
		<occluded>0</occluded>
		<bndbox>
			<xmin>107</xmin>
			<xmax>185</xmax>
			<ymin>135</ymin>
			<ymax>243</ymax>
		</bndbox>
	</object>
	<object>
		<name>power supply</name>
		<pose>Unspecified</pose>
		<truncated>0</truncated>
		<difficult>0</difficult>
		<occluded>0</occluded>
		<bndbox>
			<xmin>1</xmin>
			<xmax>94</xmax>
			<ymin>187</ymin>
			<ymax>415</ymax>
		</bndbox>
	</object>
	<object>
		<name>socket</name>
		<pose>Unspecified</pose>
		<truncated>0</truncated>
		<difficult>0</difficult>
		<occluded>0</occluded>
		<bndbox>
			<xmin>221</xmin>
			<xmax>303</xmax>
			<ymin>170</ymin>
			<ymax>292</ymax>
		</bndbox>
	</object>
	<object>
		<name>oscilloscope</name>
		<pose>Unspecified</pose>
		<truncated>0</truncated>
		<difficult>0</difficult>
		<occluded>0</occluded>
		<bndbox>
			<xmin>295</xmin>
			<xmax>417</xmax>
			<ymin>293</ymin>
			<ymax>414</ymax>
		</bndbox>
	</object>
	<object>
		<name>hand</name>
		<pose>Unspecified</pose>
		<truncated>0</truncated>
		<difficult>0</difficult>
		<occluded>0</occluded>
		<bndbox>
			<xmin>111</xmin>
			<xmax>175</xmax>
			<ymin>211</ymin>
			<ymax>351</ymax>
		</bndbox>
	</object>
</annotation>
