<annotation>
	<folder></folder>
	<filename>86_7257_jpg.rf.2c4436843053af8abfb7091e9db6c44b.jpg</filename>
	<path>86_7257_jpg.rf.2c4436843053af8abfb7091e9db6c44b.jpg</path>
	<source>
		<database>roboflow.ai</database>
	</source>
	<size>
		<width>416</width>
		<height>416</height>
		<depth>3</depth>
	</size>
	<segmented>0</segmented>
	<object>
		<name>screwdriver-</name>
		<pose>Unspecified</pose>
		<truncated>0</truncated>
		<difficult>0</difficult>
		<occluded>0</occluded>
		<bndbox>
			<xmin>153</xmin>
			<xmax>203</xmax>
			<ymin>73</ymin>
			<ymax>206</ymax>
		</bndbox>
	</object>
	<object>
		<name>low voltage board</name>
		<pose>Unspecified</pose>
		<truncated>0</truncated>
		<difficult>0</difficult>
		<occluded>0</occluded>
		<bndbox>
			<xmin>118</xmin>
			<xmax>299</xmax>
			<ymin>203</ymin>
			<ymax>416</ymax>
		</bndbox>
	</object>
	<object>
		<name>oscilloscope</name>
		<pose>Unspecified</pose>
		<truncated>0</truncated>
		<difficult>0</difficult>
		<occluded>0</occluded>
		<bndbox>
			<xmin>3</xmin>
			<xmax>152</xmax>
			<ymin>33</ymin>
			<ymax>193</ymax>
		</bndbox>
	</object>
	<object>
		<name>welder station</name>
		<pose>Unspecified</pose>
		<truncated>0</truncated>
		<difficult>0</difficult>
		<occluded>0</occluded>
		<bndbox>
			<xmin>301</xmin>
			<xmax>331</xmax>
			<ymin>149</ymin>
			<ymax>177</ymax>
		</bndbox>
	</object>
	<object>
		<name>pliers</name>
		<pose>Unspecified</pose>
		<truncated>0</truncated>
		<difficult>0</difficult>
		<occluded>0</occluded>
		<bndbox>
			<xmin>206</xmin>
			<xmax>217</xmax>
			<ymin>183</ymin>
			<ymax>200</ymax>
		</bndbox>
	</object>
	<object>
		<name>working area</name>
		<pose>Unspecified</pose>
		<truncated>0</truncated>
		<difficult>0</difficult>
		<occluded>0</occluded>
		<bndbox>
			<xmin>4</xmin>
			<xmax>372</xmax>
			<ymin>246</ymin>
			<ymax>413</ymax>
		</bndbox>
	</object>
	<object>
		<name>hand</name>
		<pose>Unspecified</pose>
		<truncated>0</truncated>
		<difficult>0</difficult>
		<occluded>0</occluded>
		<bndbox>
			<xmin>148</xmin>
			<xmax>308</xmax>
			<ymin>3</ymin>
			<ymax>156</ymax>
		</bndbox>
	</object>
	<object>
		<name>hand</name>
		<pose>Unspecified</pose>
		<truncated>0</truncated>
		<difficult>0</difficult>
		<occluded>0</occluded>
		<bndbox>
			<xmin>78</xmin>
			<xmax>143</xmax>
			<ymin>235</ymin>
			<ymax>395</ymax>
		</bndbox>
	</object>
</annotation>
